docsdk/__init__.py
docsdk/config.py
docsdk/docsdkrestclient.py
docsdk/environment_vars.py
docsdk/job.py
docsdk/resource.py
docsdk/task.py
docsdk/utils.py
docsdk/webhook.py
docsdk/exceptions/__init__.py
docsdk/exceptions/exceptions.py
tests/__init__.py
tests/integration/__init__.py
tests/integration/testJobs.py
tests/integration/testTasks.py
tests/unit/__init__.py
tests/unit/testJob.py
tests/unit/testTask.py
tests/unit/testWebhookSignature.py
docsdk-2.0.2.dist-info/LICENSE
docsdk-2.0.2.dist-info/METADATA
docsdk-2.0.2.dist-info/WHEEL
docsdk-2.0.2.dist-info/top_level.txt
docsdk-2.0.2.dist-info/RECORD
