Metadata-Version: 2.1
Name: docsdk
Version: 2.0.2
Summary: Python REST API wrapper for docsdk
Home-page: https://github.com/docsdk/docsdk-python
Author: ChenMing
Author-email: chenming@9yuntu.com
License: UNKNOWN
Platform: UNKNOWN
Classifier: Programming Language :: Python :: 3
Classifier: License :: OSI Approved :: MIT License
Classifier: Operating System :: OS Independent
Requires-Dist: requests
Requires-Dist: urllib3
